random_password_generator/__init__.py
random_password_generator/generator.py
akhil_unique_password-0.1.0.dist-info/METADATA
akhil_unique_password-0.1.0.dist-info/WHEEL
akhil_unique_password-0.1.0.dist-info/top_level.txt
akhil_unique_password-0.1.0.dist-info/RECORD
