Metadata-Version: 2.1
Name: akhil-unique-password
Version: 0.1.0
Summary: A simple Python library for generating random passwords
Home-page: https://github.com/yourusername/random-password-generator
Author: Akhil Siddabattula
Author-email: akhilsiddabattula@gmail.com
Classifier: Programming Language :: Python :: 3
Classifier: License :: OSI Approved :: MIT License
Classifier: Operating System :: OS Independent
Requires-Python: >=3.6
